qdtrader/__init__.py
qdtrader/prodtables.py
qdtrader/qeaccount.py
qdtrader/qearbit.py
qdtrader/qeasyncdata.py
qdtrader/qeasyncstrat.py
qdtrader/qebacktestmul.py
qdtrader/qecontext.py
qdtrader/qectpconst_wrap.py
qdtrader/qectpmarket.py
qdtrader/qectpmarket_wrap.py
qdtrader/qectptrader.py
qdtrader/qectptrader_wrap.py
qdtrader/qeglobal.py
qdtrader/qehtstrader.py
qdtrader/qeinterface.py
qdtrader/qelogger.py
qdtrader/qemain.py
qdtrader/qemonitor_log_web.py
qdtrader/qeoption.py
qdtrader/qeplugins.py
qdtrader/qeredisdb.py
qdtrader/qeriskctl.py
qdtrader/qesimtrader.py
qdtrader/qestatistics.py
qdtrader/qestockmarket.py
qdtrader/qestratmarket_wrap.py
qdtrader/qestratprocess.py
qdtrader/qesysconf.py
qdtrader/qetype.py
qdtrader/qeudpclient.py
qdtrader/qeweb.py
qdtrader/sysconfig.json
qdtrader/linux/qestockmarket.py
qdtrader/linux/pytransform/__init__.py
qdtrader/linux/pytransform/_pytransform.so
qdtrader/static/canvas.js
qdtrader/static/jquery.pagination.js
qdtrader/static/jquery.timers.js
qdtrader/static/theme.css
qdtrader/templates/backtest.html
qdtrader/templates/base.html
qdtrader/templates/fundhome.html
qdtrader/templates/image_all.html
qdtrader/templates/image_ex.html
qdtrader/win/qestockmarket.py
qdtrader/win/pytransform/__init__.py
qdtrader/win/pytransform/_pytransform.dll
qdtrader-0.0.4.dist-info/LICENSE
qdtrader-0.0.4.dist-info/METADATA
qdtrader-0.0.4.dist-info/WHEEL
qdtrader-0.0.4.dist-info/top_level.txt
qdtrader-0.0.4.dist-info/RECORD
