Metadata-Version: 2.1
Name: qdtrader
Version: 0.0.4
Summary: QuantDo Trader SDK for quants
Author-email: Fisher Yu <yuzs@quantdo.com.cn>
License: MIT License
Project-URL: Homepage, https://doc.quantdo.com.cn/helpbook/index.html#/cn/qdsdk/0.0.1/README
Classifier: Programming Language :: Python :: 3
Classifier: License :: OSI Approved :: MIT License
Classifier: Operating System :: OS Independent
Requires-Python: >=3.7
License-File: LICENSE
Requires-Dist: chinese-calendar >=1.9.0
Requires-Dist: Cython >=3.0.10
Requires-Dist: ctpwrapper >=6.6.9
Requires-Dist: Flask >=1.1.1
Requires-Dist: Flask-Bootstrap >=3.3.7.1
Requires-Dist: Flask-Compress >=1.12
Requires-Dist: matplotlib >=3.8.4
Requires-Dist: nest-asyncio >=1.5.5
Requires-Dist: numpy >=1.21.6
Requires-Dist: pandas >=2.2.2
Requires-Dist: python-dateutil >=2.8.2
Requires-Dist: qdsdk >=0.0.5
Requires-Dist: quantstats >=0.0.59
Requires-Dist: redis >=5.0.4
Requires-Dist: scipy >=1.13.0
Requires-Dist: passlib >=1.7.4
